{"Covers":[{"CoverID":"5244","Rating":"5","Official":"0","Username":"KYOA5","FileSize":"734","UploadedDate":"2013-06-05 00:00:00","NoRate":true},{"CoverID":"5278","Rating":"0","Official":"0","Username":"Mectbt","FileSize":"371","UploadedDate":"2013-06-10 00:00:00","NoRate":true},{"CoverID":"5255","Rating":"0","Official":"0","Username":"mouarf","FileSize":"440","UploadedDate":"2013-06-06 00:00:00","NoRate":true},{"CoverID":"28216","Rating":null,"Official":"0","Username":"NizarStore","FileSize":"409","UploadedDate":"2025-01-30 00:00:00","NoRate":true},{"CoverID":"28217","Rating":null,"Official":"0","Username":"NizarStore","FileSize":"376","UploadedDate":"2025-01-30 00:00:00","NoRate":true},{"CoverID":"28218","Rating":null,"Official":"0","Username":"NizarStore","FileSize":"425","UploadedDate":"2025-01-30 00:00:00","NoRate":true},{"CoverID":"28223","Rating":null,"Official":"0","Username":"NizarStore","FileSize":"434","UploadedDate":"2025-01-30 00:00:00","NoRate":true},{"CoverID":"28224","Rating":null,"Official":"0","Username":"NizarStore","FileSize":"381","UploadedDate":"2025-01-30 00:00:00","NoRate":true},{"CoverID":"28225","Rating":null,"Official":"0","Username":"NizarStore","FileSize":"430","UploadedDate":"2025-01-30 00:00:00","NoRate":true},{"CoverID":"28226","Rating":null,"Official":"0","Username":"NizarStore","FileSize":"369","UploadedDate":"2025-01-30 00:00:00","NoRate":true},{"CoverID":"28227","Rating":null,"Official":"0","Username":"NizarStore","FileSize":"387","UploadedDate":"2025-01-30 00:00:00","NoRate":true},{"CoverID":"28228","Rating":null,"Official":"0","Username":"NizarStore","FileSize":"415","UploadedDate":"2025-01-30 00:00:00","NoRate":true},{"CoverID":"27978","Rating":null,"Official":"0","Username":"Autopoietico ","FileSize":"1013","UploadedDate":"2024-11-29 00:00:00","NoRate":true},{"CoverID":"27979","Rating":null,"Official":"0","Username":"Autopoietico ","FileSize":"972","UploadedDate":"2024-11-29 00:00:00","NoRate":true},{"CoverID":"27729","Rating":null,"Official":"0","Username":"stiven2326","FileSize":"64","UploadedDate":"2024-09-07 00:00:00","NoRate":true},{"CoverID":"27659","Rating":null,"Official":"0","Username":"wooferyo","FileSize":"1005","UploadedDate":"2024-08-17 00:00:00","NoRate":true},{"CoverID":"27660","Rating":null,"Official":"0","Username":"wooferyo","FileSize":"172","UploadedDate":"2024-08-17 00:00:00","NoRate":true},{"CoverID":"27662","Rating":null,"Official":"0","Username":"wooferyo","FileSize":"191","UploadedDate":"2024-08-17 00:00:00","NoRate":true},{"CoverID":"27663","Rating":null,"Official":"0","Username":"wooferyo","FileSize":"490","UploadedDate":"2024-08-17 00:00:00","NoRate":true},{"CoverID":"27664","Rating":null,"Official":"0","Username":"wooferyo","FileSize":"575","UploadedDate":"2024-08-17 00:00:00","NoRate":true},{"CoverID":"27565","Rating":null,"Official":"0","Username":"NizarModz","FileSize":"916","UploadedDate":"2024-06-05 00:00:00","NoRate":true},{"CoverID":"26812","Rating":null,"Official":"0","Username":"MsULTIMATEMAX","FileSize":"2113","UploadedDate":"2023-10-22 00:00:00","NoRate":true},{"CoverID":"26325","Rating":null,"Official":"0","Username":"TheNameOFF","FileSize":"153","UploadedDate":"2023-03-11 00:00:00","NoRate":true},{"CoverID":"25817","Rating":null,"Official":"0","Username":"antukent","FileSize":"802","UploadedDate":"2022-10-01 00:00:00","NoRate":true},{"CoverID":"24941","Rating":null,"Official":"0","Username":"julio08161","FileSize":"715","UploadedDate":"2021-07-11 00:00:00","NoRate":true},{"CoverID":"24942","Rating":null,"Official":"0","Username":"julio08161","FileSize":"771","UploadedDate":"2021-07-11 00:00:00","NoRate":true},{"CoverID":"24590","Rating":null,"Official":"1","Username":"danito_bon43","FileSize":"292","UploadedDate":"2021-04-21 00:00:00","NoRate":true},{"CoverID":"24525","Rating":null,"Official":"0","Username":"Zaikrot","FileSize":"378","UploadedDate":"2021-04-03 00:00:00","NoRate":true},{"CoverID":"24485","Rating":null,"Official":"0","Username":"pako blue fox","FileSize":"125","UploadedDate":"2021-03-09 00:00:00","NoRate":true},{"CoverID":"24486","Rating":null,"Official":"0","Username":"pako blue fox","FileSize":"190","UploadedDate":"2021-03-09 00:00:00","NoRate":true},{"CoverID":"24487","Rating":null,"Official":"0","Username":"pako blue fox","FileSize":"191","UploadedDate":"2021-03-09 00:00:00","NoRate":true},{"CoverID":"24488","Rating":null,"Official":"0","Username":"pako blue fox","FileSize":"125","UploadedDate":"2021-03-09 00:00:00","NoRate":true},{"CoverID":"24489","Rating":null,"Official":"0","Username":"pako blue fox","FileSize":"191","UploadedDate":"2021-03-09 00:00:00","NoRate":true},{"CoverID":"24490","Rating":null,"Official":"0","Username":"pako blue fox","FileSize":"190","UploadedDate":"2021-03-09 00:00:00","NoRate":true},{"CoverID":"24484","Rating":null,"Official":"0","Username":"pako blue fox","FileSize":"621","UploadedDate":"2021-03-08 00:00:00","NoRate":true},{"CoverID":"24163","Rating":null,"Official":"0","Username":"TheGabo","FileSize":"904","UploadedDate":"2020-09-19 00:00:00","NoRate":true},{"CoverID":"24164","Rating":null,"Official":"0","Username":"TheGabo","FileSize":"903","UploadedDate":"2020-09-19 00:00:00","NoRate":true},{"CoverID":"24165","Rating":null,"Official":"0","Username":"TheGabo","FileSize":"1037","UploadedDate":"2020-09-19 00:00:00","NoRate":true},{"CoverID":"24166","Rating":null,"Official":"0","Username":"TheGabo","FileSize":"808","UploadedDate":"2020-09-19 00:00:00","NoRate":true},{"CoverID":"24167","Rating":null,"Official":"0","Username":"TheGabo","FileSize":"1051","UploadedDate":"2020-09-19 00:00:00","NoRate":true},{"CoverID":"24168","Rating":null,"Official":"0","Username":"TheGabo","FileSize":"869","UploadedDate":"2020-09-19 00:00:00","NoRate":true},{"CoverID":"24169","Rating":null,"Official":"0","Username":"TheGabo","FileSize":"769","UploadedDate":"2020-09-19 00:00:00","NoRate":true},{"CoverID":"24170","Rating":null,"Official":"0","Username":"TheGabo","FileSize":"902","UploadedDate":"2020-09-19 00:00:00","NoRate":true},{"CoverID":"24171","Rating":null,"Official":"0","Username":"TheGabo","FileSize":"968","UploadedDate":"2020-09-19 00:00:00","NoRate":true},{"CoverID":"24172","Rating":null,"Official":"0","Username":"TheGabo","FileSize":"1008","UploadedDate":"2020-09-19 00:00:00","NoRate":true},{"CoverID":"24173","Rating":null,"Official":"0","Username":"TheGabo","FileSize":"933","UploadedDate":"2020-09-19 00:00:00","NoRate":true},{"CoverID":"24174","Rating":null,"Official":"0","Username":"TheGabo","FileSize":"937","UploadedDate":"2020-09-19 00:00:00","NoRate":true},{"CoverID":"24175","Rating":null,"Official":"0","Username":"TheGabo","FileSize":"947","UploadedDate":"2020-09-19 00:00:00","NoRate":true},{"CoverID":"24136","Rating":null,"Official":"0","Username":"Zombiesaurio","FileSize":"296","UploadedDate":"2020-08-09 00:00:00","NoRate":true},{"CoverID":"23598","Rating":null,"Official":"1","Username":"MushroomKnight","FileSize":"607","UploadedDate":"2019-07-31 00:00:00","NoRate":true},{"CoverID":"23368","Rating":null,"Official":"0","Username":"Kaltenbruner","FileSize":"846","UploadedDate":"2019-03-05 00:00:00","NoRate":true},{"CoverID":"23369","Rating":null,"Official":"0","Username":"Kaltenbruner","FileSize":"873","UploadedDate":"2019-03-05 00:00:00","NoRate":true},{"CoverID":"23370","Rating":null,"Official":"0","Username":"Kaltenbruner","FileSize":"698","UploadedDate":"2019-03-05 00:00:00","NoRate":true},{"CoverID":"23371","Rating":null,"Official":"0","Username":"Kaltenbruner","FileSize":"798","UploadedDate":"2019-03-05 00:00:00","NoRate":true},{"CoverID":"23372","Rating":null,"Official":"0","Username":"Kaltenbruner","FileSize":"962","UploadedDate":"2019-03-05 00:00:00","NoRate":true},{"CoverID":"23373","Rating":null,"Official":"0","Username":"Kaltenbruner","FileSize":"1048","UploadedDate":"2019-03-05 00:00:00","NoRate":true},{"CoverID":"23374","Rating":null,"Official":"0","Username":"Kaltenbruner","FileSize":"696","UploadedDate":"2019-03-05 00:00:00","NoRate":true},{"CoverID":"23375","Rating":null,"Official":"0","Username":"Kaltenbruner","FileSize":"236","UploadedDate":"2019-03-05 00:00:00","NoRate":true},{"CoverID":"23323","Rating":null,"Official":"0","Username":"darksikx","FileSize":"102","UploadedDate":"2019-02-13 00:00:00","NoRate":true},{"CoverID":"22938","Rating":null,"Official":"0","Username":"Kaltenbruner","FileSize":"632","UploadedDate":"2018-08-15 00:00:00","NoRate":true},{"CoverID":"22878","Rating":null,"Official":"0","Username":"tallaito","FileSize":"356","UploadedDate":"2018-07-20 00:00:00","NoRate":true},{"CoverID":"22359","Rating":null,"Official":"0","Username":"tallaito","FileSize":"146","UploadedDate":"2018-03-12 00:00:00","NoRate":true},{"CoverID":"22360","Rating":null,"Official":"0","Username":"tallaito","FileSize":"199","UploadedDate":"2018-03-12 00:00:00","NoRate":true},{"CoverID":"22140","Rating":null,"Official":"0","Username":"akatsuki-ghost","FileSize":"752","UploadedDate":"2018-01-31 00:00:00","NoRate":true},{"CoverID":"22076","Rating":null,"Official":"0","Username":"odera","FileSize":"252","UploadedDate":"2018-01-17 00:00:00","NoRate":true},{"CoverID":"22077","Rating":null,"Official":"0","Username":"odera","FileSize":"233","UploadedDate":"2018-01-17 00:00:00","NoRate":true},{"CoverID":"22078","Rating":null,"Official":"0","Username":"odera","FileSize":"303","UploadedDate":"2018-01-17 00:00:00","NoRate":true},{"CoverID":"22079","Rating":null,"Official":"0","Username":"odera","FileSize":"317","UploadedDate":"2018-01-17 00:00:00","NoRate":true},{"CoverID":"22080","Rating":null,"Official":"0","Username":"odera","FileSize":"250","UploadedDate":"2018-01-17 00:00:00","NoRate":true},{"CoverID":"22081","Rating":null,"Official":"0","Username":"odera","FileSize":"318","UploadedDate":"2018-01-17 00:00:00","NoRate":true},{"CoverID":"22082","Rating":null,"Official":"0","Username":"odera","FileSize":"250","UploadedDate":"2018-01-17 00:00:00","NoRate":true},{"CoverID":"22083","Rating":null,"Official":"0","Username":"odera","FileSize":"231","UploadedDate":"2018-01-17 00:00:00","NoRate":true},{"CoverID":"22084","Rating":null,"Official":"0","Username":"odera","FileSize":"283","UploadedDate":"2018-01-17 00:00:00","NoRate":true},{"CoverID":"22085","Rating":null,"Official":"0","Username":"odera","FileSize":"292","UploadedDate":"2018-01-17 00:00:00","NoRate":true},{"CoverID":"22086","Rating":null,"Official":"0","Username":"odera","FileSize":"287","UploadedDate":"2018-01-17 00:00:00","NoRate":true},{"CoverID":"21768","Rating":null,"Official":"0","Username":"pendulume","FileSize":"842","UploadedDate":"2017-10-10 00:00:00","NoRate":true},{"CoverID":"21759","Rating":null,"Official":"0","Username":"gameplay00","FileSize":"186","UploadedDate":"2017-10-06 00:00:00","NoRate":true},{"CoverID":"21470","Rating":null,"Official":"0","Username":"Ryoma1217","FileSize":"544","UploadedDate":"2017-09-16 00:00:00","NoRate":true},{"CoverID":"21471","Rating":null,"Official":"0","Username":"Ryoma1217","FileSize":"551","UploadedDate":"2017-09-16 00:00:00","NoRate":true},{"CoverID":"21455","Rating":null,"Official":"0","Username":"Ryoma1217","FileSize":"473","UploadedDate":"2017-09-14 00:00:00","NoRate":true},{"CoverID":"21456","Rating":null,"Official":"0","Username":"Ryoma1217","FileSize":"551","UploadedDate":"2017-09-14 00:00:00","NoRate":true},{"CoverID":"21457","Rating":null,"Official":"0","Username":"Ryoma1217","FileSize":"545","UploadedDate":"2017-09-14 00:00:00","NoRate":true},{"CoverID":"21451","Rating":null,"Official":"0","Username":"Ryoma1217","FileSize":"492","UploadedDate":"2017-09-13 00:00:00","NoRate":true},{"CoverID":"21452","Rating":null,"Official":"0","Username":"Ryoma1217","FileSize":"519","UploadedDate":"2017-09-13 00:00:00","NoRate":true},{"CoverID":"21442","Rating":null,"Official":"0","Username":"ZIDDX","FileSize":"261","UploadedDate":"2017-09-10 00:00:00","NoRate":true},{"CoverID":"21431","Rating":null,"Official":"0","Username":"Ryoma1217","FileSize":"861","UploadedDate":"2017-09-09 00:00:00","NoRate":true},{"CoverID":"21435","Rating":null,"Official":"0","Username":"Ryoma1217","FileSize":"824","UploadedDate":"2017-09-09 00:00:00","NoRate":true},{"CoverID":"21200","Rating":null,"Official":"0","Username":"andres16062013","FileSize":"113","UploadedDate":"2017-06-07 00:00:00","NoRate":true},{"CoverID":"21201","Rating":null,"Official":"0","Username":"andres16062013","FileSize":"751","UploadedDate":"2017-06-07 00:00:00","NoRate":true},{"CoverID":"20831","Rating":null,"Official":"0","Username":"farrell vazquez","FileSize":"735","UploadedDate":"2017-02-05 00:00:00","NoRate":true},{"CoverID":"20832","Rating":null,"Official":"0","Username":"farrell vazquez","FileSize":"743","UploadedDate":"2017-02-05 00:00:00","NoRate":true},{"CoverID":"20833","Rating":null,"Official":"0","Username":"farrell vazquez","FileSize":"758","UploadedDate":"2017-02-05 00:00:00","NoRate":true},{"CoverID":"20734","Rating":null,"Official":"0","Username":"kianjoik","FileSize":"497","UploadedDate":"2017-01-13 00:00:00","NoRate":true},{"CoverID":"20211","Rating":null,"Official":"0","Username":"pesxdz","FileSize":"601","UploadedDate":"2016-10-29 00:00:00","NoRate":true},{"CoverID":"20193","Rating":null,"Official":"0","Username":"smokemonster","FileSize":"213","UploadedDate":"2016-10-28 00:00:00","NoRate":true},{"CoverID":"20191","Rating":null,"Official":"0","Username":"pesxdz","FileSize":"601","UploadedDate":"2016-10-27 00:00:00","NoRate":true},{"CoverID":"14594","Rating":null,"Official":"0","Username":"nero3480","FileSize":"50","UploadedDate":"2015-08-20 00:00:00","NoRate":true},{"CoverID":"13343","Rating":null,"Official":"0","Username":"pesxdz","FileSize":"770","UploadedDate":"2015-04-25 00:00:00","NoRate":true},{"CoverID":"13324","Rating":null,"Official":"0","Username":"pesxdz","FileSize":"789","UploadedDate":"2015-04-23 00:00:00","NoRate":true},{"CoverID":"12970","Rating":null,"Official":"0","Username":"tallaito","FileSize":"630","UploadedDate":"2015-03-24 00:00:00","NoRate":true},{"CoverID":"12364","Rating":null,"Official":"0","Username":"MushroomKnight","FileSize":"407","UploadedDate":"2015-02-10 00:00:00","NoRate":true},{"CoverID":"11701","Rating":null,"Official":"0","Username":"HALISSON","FileSize":"104","UploadedDate":"2015-01-24 00:00:00","NoRate":true},{"CoverID":"11942","Rating":null,"Official":"0","Username":"pesxdz","FileSize":"593","UploadedDate":"2015-01-24 00:00:00","NoRate":true},{"CoverID":"11608","Rating":null,"Official":"0","Username":"HALISSON","FileSize":"172","UploadedDate":"2015-01-22 00:00:00","NoRate":true},{"CoverID":"11609","Rating":null,"Official":"0","Username":"HALISSON","FileSize":"128","UploadedDate":"2015-01-22 00:00:00","NoRate":true},{"CoverID":"11164","Rating":null,"Official":"0","Username":"Lurker","FileSize":"343","UploadedDate":"2015-01-03 00:00:00","NoRate":true}],"CoversCount":106}