{"Covers":[{"CoverID":"4988","Rating":"5","Official":"1","Username":"Ruiz357","FileSize":"433","UploadedDate":"2013-04-21 00:00:00","NoRate":true},{"CoverID":"4358","Rating":"1","Official":"1","Username":"creamskull","FileSize":"308","UploadedDate":"2012-12-02 00:00:00","NoRate":true},{"CoverID":"13394","Rating":null,"Official":"0","Username":"RianLivre2099","FileSize":"302","UploadedDate":"2015-04-28 00:00:00","NoRate":true},{"CoverID":"13251","Rating":null,"Official":"0","Username":"gorrolana73","FileSize":"266","UploadedDate":"2015-04-19 00:00:00","NoRate":true},{"CoverID":"10360","Rating":null,"Official":"0","Username":"Sisee","FileSize":"1112","UploadedDate":"2014-11-22 00:00:00","NoRate":true},{"CoverID":"9709","Rating":null,"Official":"0","Username":"QuattroGam3r","FileSize":"204","UploadedDate":"2014-11-06 00:00:00","NoRate":true}],"CoversCount":6}