{"Covers":[{"CoverID":"5917","Rating":"0","Official":"0","Username":"absolon","FileSize":"197","UploadedDate":"2013-10-20 00:00:00","NoRate":true},{"CoverID":"28110","Rating":null,"Official":"0","Username":"Dimarik0277","FileSize":"280","UploadedDate":"2024-12-05 00:00:00","NoRate":true},{"CoverID":"17925","Rating":null,"Official":"0","Username":"Casperr","FileSize":"337","UploadedDate":"2016-01-02 00:00:00","NoRate":true},{"CoverID":"10397","Rating":null,"Official":"0","Username":"Goderk","FileSize":"377","UploadedDate":"2014-11-23 00:00:00","NoRate":true}],"CoversCount":4}