{"Covers":[{"CoverID":"737","Rating":"0","Official":"1","Username":"TraJiK","FileSize":"112","UploadedDate":"2011-02-25 00:00:00","NoRate":true},{"CoverID":"27049","Rating":null,"Official":"0","Username":"GermanTron","FileSize":"830","UploadedDate":"2023-12-06 00:00:00","NoRate":true},{"CoverID":"22241","Rating":null,"Official":"0","Username":"linewalker90","FileSize":"902","UploadedDate":"2018-02-19 00:00:00","NoRate":true},{"CoverID":"17753","Rating":null,"Official":"0","Username":"Casperr","FileSize":"333","UploadedDate":"2016-01-01 00:00:00","NoRate":true},{"CoverID":"10171","Rating":null,"Official":"0","Username":"Sisee","FileSize":"854","UploadedDate":"2014-11-16 00:00:00","NoRate":true}],"CoversCount":5}