{"Covers":[{"CoverID":"5358","Rating":"0","Official":"0","Username":"HairyBones","FileSize":"238","UploadedDate":"2013-06-25 00:00:00","NoRate":true},{"CoverID":"28132","Rating":null,"Official":"0","Username":"Dimarik0277","FileSize":"1038","UploadedDate":"2024-12-05 00:00:00","NoRate":true},{"CoverID":"26402","Rating":null,"Official":"0","Username":"Kawan_santos","FileSize":"182","UploadedDate":"2023-04-29 00:00:00","NoRate":true},{"CoverID":"26407","Rating":null,"Official":"0","Username":"Kawan_santos","FileSize":"182","UploadedDate":"2023-04-29 00:00:00","NoRate":true},{"CoverID":"18018","Rating":null,"Official":"0","Username":"Casperr","FileSize":"355","UploadedDate":"2016-01-02 00:00:00","NoRate":true},{"CoverID":"10741","Rating":null,"Official":"0","Username":"Goderk","FileSize":"473","UploadedDate":"2014-12-12 00:00:00","NoRate":true}],"CoversCount":6}