{"Covers":[{"CoverID":"2526","Rating":"5","Official":"0","Username":"JPizzle","FileSize":"543","UploadedDate":"2011-09-02 00:00:00","NoRate":true},{"CoverID":"27011","Rating":null,"Official":"0","Username":"GermanTron","FileSize":"796","UploadedDate":"2023-12-04 00:00:00","NoRate":true},{"CoverID":"26170","Rating":null,"Official":"1","Username":"blzzs","FileSize":"151","UploadedDate":"2023-01-12 00:00:00","NoRate":true},{"CoverID":"26130","Rating":null,"Official":"0","Username":"matt9","FileSize":"789","UploadedDate":"2023-01-04 00:00:00","NoRate":true},{"CoverID":"8458","Rating":null,"Official":"0","Username":"Lurker","FileSize":"208","UploadedDate":"2014-09-16 00:00:00","NoRate":true},{"CoverID":"8459","Rating":null,"Official":"0","Username":"Lurker","FileSize":"215","UploadedDate":"2014-09-16 00:00:00","NoRate":true}],"CoversCount":6}