{"Covers":[{"CoverID":"3489","Rating":"4","Official":"0","Username":"square90","FileSize":"227","UploadedDate":"2012-06-12 00:00:00","NoRate":true},{"CoverID":"27915","Rating":null,"Official":"1","Username":"IChoseRapture95","FileSize":"577","UploadedDate":"2024-10-20 00:00:00","NoRate":true},{"CoverID":"24233","Rating":null,"Official":"0","Username":"SupershalloBoy","FileSize":"741","UploadedDate":"2020-10-25 00:00:00","NoRate":true},{"CoverID":"15565","Rating":null,"Official":"0","Username":"KILLERPAPA23","FileSize":"327","UploadedDate":"2015-11-21 00:00:00","NoRate":true},{"CoverID":"11750","Rating":null,"Official":"0","Username":"alice989","FileSize":"116","UploadedDate":"2015-01-24 00:00:00","NoRate":true},{"CoverID":"11449","Rating":null,"Official":"0","Username":"decxx1","FileSize":"225","UploadedDate":"2015-01-12 00:00:00","NoRate":true},{"CoverID":"11450","Rating":null,"Official":"0","Username":"decxx1","FileSize":"253","UploadedDate":"2015-01-12 00:00:00","NoRate":true},{"CoverID":"11451","Rating":null,"Official":"0","Username":"decxx1","FileSize":"255","UploadedDate":"2015-01-12 00:00:00","NoRate":true},{"CoverID":"11452","Rating":null,"Official":"0","Username":"decxx1","FileSize":"589","UploadedDate":"2015-01-12 00:00:00","NoRate":true},{"CoverID":"11453","Rating":null,"Official":"0","Username":"decxx1","FileSize":"597","UploadedDate":"2015-01-12 00:00:00","NoRate":true},{"CoverID":"9815","Rating":null,"Official":"0","Username":"Sisee","FileSize":"1048","UploadedDate":"2014-11-08 00:00:00","NoRate":true}],"CoversCount":11}