{"Covers":[{"CoverID":"1267","Rating":"0","Official":"0","Username":"mdd45","FileSize":"572","UploadedDate":"2011-03-15 00:00:00","NoRate":true},{"CoverID":"23774","Rating":null,"Official":"0","Username":"matt9","FileSize":"780","UploadedDate":"2019-12-23 00:00:00","NoRate":true},{"CoverID":"19259","Rating":null,"Official":"0","Username":"Roberto3","FileSize":"268","UploadedDate":"2016-05-06 00:00:00","NoRate":true},{"CoverID":"11293","Rating":null,"Official":"0","Username":"bienv1","FileSize":"1024","UploadedDate":"2015-01-06 00:00:00","NoRate":true}],"CoversCount":4}