{"Covers":[{"CoverID":"27085","Rating":null,"Official":"0","Username":"GermanTron","FileSize":"833","UploadedDate":"2023-12-06 00:00:00","NoRate":true},{"CoverID":"26329","Rating":null,"Official":"0","Username":"flavitcho","FileSize":"348","UploadedDate":"2023-03-19 00:00:00","NoRate":true},{"CoverID":"23867","Rating":null,"Official":"0","Username":"BroBas00","FileSize":"1065","UploadedDate":"2020-02-15 00:00:00","NoRate":true},{"CoverID":"23593","Rating":null,"Official":"1","Username":"MushroomKnight","FileSize":"765","UploadedDate":"2019-07-31 00:00:00","NoRate":true},{"CoverID":"21874","Rating":null,"Official":"0","Username":"MoBy41","FileSize":"929","UploadedDate":"2017-11-12 00:00:00","NoRate":true},{"CoverID":"20637","Rating":null,"Official":"0","Username":"Casperr","FileSize":"384","UploadedDate":"2016-12-27 00:00:00","NoRate":true},{"CoverID":"19674","Rating":null,"Official":"0","Username":"Sakitoshi","FileSize":"1235","UploadedDate":"2016-08-19 00:00:00","NoRate":true},{"CoverID":"19671","Rating":null,"Official":"0","Username":"xxXDangoXxx","FileSize":"356","UploadedDate":"2016-08-18 00:00:00","NoRate":true},{"CoverID":"19393","Rating":null,"Official":"0","Username":"SAMUELORD","FileSize":"710","UploadedDate":"2016-06-27 00:00:00","NoRate":true},{"CoverID":"19387","Rating":null,"Official":"0","Username":"mtrmestre","FileSize":"1156","UploadedDate":"2016-06-27 00:00:00","NoRate":true},{"CoverID":"19388","Rating":null,"Official":"0","Username":"ks303","FileSize":"902","UploadedDate":"2016-06-27 00:00:00","NoRate":true},{"CoverID":"19389","Rating":null,"Official":"0","Username":"SAMUELORD","FileSize":"710","UploadedDate":"2016-06-27 00:00:00","NoRate":true},{"CoverID":"19390","Rating":null,"Official":"0","Username":"SAMUELORD","FileSize":"538","UploadedDate":"2016-06-27 00:00:00","NoRate":true},{"CoverID":"19391","Rating":null,"Official":"0","Username":"SAMUELORD","FileSize":"604","UploadedDate":"2016-06-27 00:00:00","NoRate":true},{"CoverID":"19392","Rating":null,"Official":"0","Username":"SAMUELORD","FileSize":"579","UploadedDate":"2016-06-27 00:00:00","NoRate":true},{"CoverID":"19380","Rating":null,"Official":"0","Username":"xxXDangoXxx","FileSize":"295","UploadedDate":"2016-06-26 00:00:00","NoRate":true},{"CoverID":"19383","Rating":null,"Official":"0","Username":"mtrmestre","FileSize":"1156","UploadedDate":"2016-06-26 00:00:00","NoRate":true},{"CoverID":"19382","Rating":null,"Official":"0","Username":"mudeariesmex","FileSize":"975","UploadedDate":"2016-06-26 00:00:00","NoRate":true},{"CoverID":"19379","Rating":null,"Official":"0","Username":"xxXDangoXxx","FileSize":"295","UploadedDate":"2016-06-25 00:00:00","NoRate":true},{"CoverID":"19375","Rating":null,"Official":"0","Username":"r.gomes.1985","FileSize":"1039","UploadedDate":"2016-06-25 00:00:00","NoRate":true},{"CoverID":"19374","Rating":null,"Official":"0","Username":"Hangyodon","FileSize":"886","UploadedDate":"2016-06-25 00:00:00","NoRate":true},{"CoverID":"19363","Rating":null,"Official":"0","Username":"lucagil","FileSize":"789","UploadedDate":"2016-06-24 00:00:00","NoRate":true},{"CoverID":"19364","Rating":null,"Official":"0","Username":"Hangyodon","FileSize":"886","UploadedDate":"2016-06-24 00:00:00","NoRate":true},{"CoverID":"19365","Rating":null,"Official":"0","Username":"mtrmestre","FileSize":"1156","UploadedDate":"2016-06-24 00:00:00","NoRate":true},{"CoverID":"19372","Rating":null,"Official":"0","Username":"farkas666","FileSize":"295","UploadedDate":"2016-06-24 00:00:00","NoRate":true},{"CoverID":"19373","Rating":null,"Official":"0","Username":"crisds","FileSize":"1039","UploadedDate":"2016-06-24 00:00:00","NoRate":true},{"CoverID":"19362","Rating":null,"Official":"0","Username":"Hangyodon","FileSize":"882","UploadedDate":"2016-06-23 00:00:00","NoRate":true},{"CoverID":"19361","Rating":null,"Official":"0","Username":"BreykellGm3","FileSize":"975","UploadedDate":"2016-06-23 00:00:00","NoRate":true},{"CoverID":"19360","Rating":null,"Official":"0","Username":"rubensyama2014","FileSize":"1039","UploadedDate":"2016-06-23 00:00:00","NoRate":true},{"CoverID":"19359","Rating":null,"Official":"0","Username":"mudeariesmex","FileSize":"975","UploadedDate":"2016-06-23 00:00:00","NoRate":true},{"CoverID":"19357","Rating":null,"Official":"0","Username":"rubensyama2014","FileSize":"1039","UploadedDate":"2016-06-23 00:00:00","NoRate":true},{"CoverID":"19356","Rating":null,"Official":"0","Username":"SNAKE_8","FileSize":"1132","UploadedDate":"2016-06-23 00:00:00","NoRate":true},{"CoverID":"19355","Rating":null,"Official":"0","Username":"linewalker90","FileSize":"325","UploadedDate":"2016-06-23 00:00:00","NoRate":true},{"CoverID":"19353","Rating":null,"Official":"0","Username":"leonbert69","FileSize":"975","UploadedDate":"2016-06-23 00:00:00","NoRate":true},{"CoverID":"19350","Rating":null,"Official":"0","Username":"Miha2002","FileSize":"331","UploadedDate":"2016-06-21 00:00:00","NoRate":true}],"CoversCount":35}