{"Covers":[{"CoverID":"759","Rating":"5","Official":"1","Username":"TraJiK","FileSize":"111","UploadedDate":"2011-02-26 00:00:00","NoRate":true},{"CoverID":"20768","Rating":null,"Official":"0","Username":"MeDoo_MeDoo_Naruto","FileSize":"193","UploadedDate":"2017-01-24 00:00:00","NoRate":true},{"CoverID":"17888","Rating":null,"Official":"0","Username":"Casperr","FileSize":"354","UploadedDate":"2016-01-02 00:00:00","NoRate":true},{"CoverID":"14465","Rating":null,"Official":"0","Username":"s3RG3y06","FileSize":"190","UploadedDate":"2015-07-29 00:00:00","NoRate":true},{"CoverID":"12709","Rating":null,"Official":"0","Username":"projektHAZE","FileSize":"190","UploadedDate":"2015-03-02 00:00:00","NoRate":true}],"CoversCount":5}