{"Covers":[{"CoverID":"5361","Rating":"5","Official":"0","Username":"fuzzak","FileSize":"996","UploadedDate":"2013-06-27 00:00:00","NoRate":true},{"CoverID":"17843","Rating":null,"Official":"0","Username":"Casperr","FileSize":"339","UploadedDate":"2016-01-01 00:00:00","NoRate":true},{"CoverID":"14520","Rating":null,"Official":"0","Username":"retrogamer343","FileSize":"645","UploadedDate":"2015-08-08 00:00:00","NoRate":true},{"CoverID":"14368","Rating":null,"Official":"1","Username":"Camilleons","FileSize":"1068","UploadedDate":"2015-07-17 00:00:00","NoRate":true},{"CoverID":"9400","Rating":null,"Official":"0","Username":"FdnSL","FileSize":"666","UploadedDate":"2014-10-19 00:00:00","NoRate":true},{"CoverID":"9220","Rating":null,"Official":"0","Username":"FdnSL","FileSize":"668","UploadedDate":"2014-10-09 00:00:00","NoRate":true}],"CoversCount":6}