{"Covers":[{"CoverID":"20568","Rating":null,"Official":"0","Username":"seymorebutts","FileSize":"608","UploadedDate":"2016-12-22 00:00:00","NoRate":true},{"CoverID":"17642","Rating":null,"Official":"0","Username":"Casperr","FileSize":"362","UploadedDate":"2016-01-01 00:00:00","NoRate":true},{"CoverID":"10972","Rating":null,"Official":"0","Username":"szymonk19","FileSize":"1069","UploadedDate":"2014-12-22 00:00:00","NoRate":true},{"CoverID":"10951","Rating":null,"Official":"0","Username":"mrdude2478","FileSize":"385","UploadedDate":"2014-12-21 00:00:00","NoRate":true}],"CoversCount":4}