{"Covers":[{"CoverID":"1101","Rating":"5","Official":"0","Username":"TraJiK","FileSize":"612","UploadedDate":"2011-03-07 00:00:00","NoRate":true},{"CoverID":"1005","Rating":"5","Official":"0","Username":"TraJiK","FileSize":"578","UploadedDate":"2011-03-06 00:00:00","NoRate":true},{"CoverID":"304","Rating":"0","Official":"1","Username":"TraJiK","FileSize":"572","UploadedDate":"2011-02-21 00:00:00","NoRate":true},{"CoverID":"24882","Rating":null,"Official":"0","Username":"Zaikrot","FileSize":"975","UploadedDate":"2021-06-19 00:00:00","NoRate":true},{"CoverID":"22207","Rating":null,"Official":"0","Username":"xboxgopaulinho","FileSize":"297","UploadedDate":"2018-02-15 00:00:00","NoRate":true},{"CoverID":"20471","Rating":null,"Official":"1","Username":"Marketplace","FileSize":"300","UploadedDate":"2016-12-09 00:00:00","NoRate":true},{"CoverID":"18685","Rating":null,"Official":"1","Username":"Joseadilson","FileSize":"264","UploadedDate":"2016-02-07 00:00:00","NoRate":true},{"CoverID":"15356","Rating":null,"Official":"0","Username":"funkuzo","FileSize":"578","UploadedDate":"2015-11-04 00:00:00","NoRate":true},{"CoverID":"14855","Rating":null,"Official":"0","Username":"SraBigBoss","FileSize":"1326","UploadedDate":"2015-09-14 00:00:00","NoRate":true},{"CoverID":"14464","Rating":null,"Official":"0","Username":"sztikk","FileSize":"657","UploadedDate":"2015-07-29 00:00:00","NoRate":true},{"CoverID":"13449","Rating":null,"Official":"0","Username":"RianLivre2099","FileSize":"284","UploadedDate":"2015-05-01 00:00:00","NoRate":true},{"CoverID":"9235","Rating":null,"Official":"0","Username":"FdnSL","FileSize":"504","UploadedDate":"2014-10-09 00:00:00","NoRate":true},{"CoverID":"9070","Rating":null,"Official":"0","Username":"Xque4ever","FileSize":"1389","UploadedDate":"2014-10-03 00:00:00","NoRate":true}],"CoversCount":13}