{"Covers":[{"CoverID":"3418","Rating":"0","Official":"1","Username":"TraJiK","FileSize":"420","UploadedDate":"2012-05-30 00:00:00","NoRate":true},{"CoverID":"19991","Rating":null,"Official":"0","Username":"smokemonster","FileSize":"1202","UploadedDate":"2016-10-11 00:00:00","NoRate":true},{"CoverID":"19992","Rating":null,"Official":"0","Username":"smokemonster","FileSize":"1271","UploadedDate":"2016-10-11 00:00:00","NoRate":true},{"CoverID":"18235","Rating":null,"Official":"0","Username":"Casperr","FileSize":"326","UploadedDate":"2016-01-03 00:00:00","NoRate":true},{"CoverID":"13528","Rating":null,"Official":"0","Username":"Sisee","FileSize":"924","UploadedDate":"2015-05-06 00:00:00","NoRate":true}],"CoversCount":5}